docstrands/__init__.py
docstrands/parsed_func.py
docstrands-0.1.0.dist-info/METADATA
docstrands-0.1.0.dist-info/WHEEL
docstrands-0.1.0.dist-info/entry_points.txt
docstrands-0.1.0.dist-info/licenses/LICENSE
docstrands-0.1.0.dist-info/RECORD
