Metadata-Version: 2.4
Name: docstrands
Version: 0.1.0
Summary: Re-use segments of your docstrings
Author-email: Michael Milton <michael.r.milton@gmail.com>
License-File: LICENSE
Requires-Python: >=3.9
Requires-Dist: docstring-parser>=0.16
Requires-Dist: typing-extensions>=4.12.2
